monnifyease/__init__.py
monnifyease/apis/__init__.py
monnifyease/apis/sync_apis/__init__.py
monnifyease/apis/sync_apis/banks.py
monnifyease/apis/sync_apis/customer_reserved_account.py
monnifyease/apis/sync_apis/settlements.py
monnifyease/apis/sync_apis/subaccounts.py
monnifyease/apis/sync_apis/transactions.py
monnifyease/apis/sync_apis/wallet.py
monnifyease/core/__init__.py
monnifyease/core/_api_access_header.py
monnifyease/core/_api_base.py
monnifyease/core/_api_base_envar.py
monnifyease/core/_api_base_request.py
monnifyease/core/_api_client_requests.py
monnifyease/core/_api_client_response.py
monnifyease/core/_api_errors.py
monnifyease/helpers/__init__.py
monnifyease/helpers/tool_kit.py
monnifyease/monnify.py
monnifyease/utils/__init__.py
monnifyease/utils/convert_to_strings.py
monnifyease/utils/join_url.py
monnifyease-0.2.0.dist-info/LICENSE
monnifyease-0.2.0.dist-info/METADATA
monnifyease-0.2.0.dist-info/WHEEL
monnifyease-0.2.0.dist-info/RECORD
