Metadata-Version: 2.1
Name: monnifyease
Version: 0.2.0
Summary: This is a Monnify API wrapper
License: MIT
Keywords: moniepoint,monnifyease,monnify,python,api,wrapper
Author: Peter Mbachu
Author-email: doublep098@gmail.com
Maintainer: petermbachu.bincom
Maintainer-email: petermbachu.bincom@gmail.com
Requires-Python: >=3.9,<4.0
Classifier: Development Status :: 5 - Production/Stable
Classifier: Intended Audience :: Developers
Classifier: License :: OSI Approved :: MIT License
Classifier: Natural Language :: English
Classifier: Operating System :: OS Independent
Classifier: Programming Language :: Python :: 3
Classifier: Programming Language :: Python :: 3.9
Classifier: Programming Language :: Python :: 3.10
Classifier: Programming Language :: Python :: 3.11
Classifier: Programming Language :: Python :: 3.12
Classifier: Topic :: Software Development :: Libraries :: Python Modules
Requires-Dist: aiohttp (>=3.8,<4.0)
Requires-Dist: python-decouple (>=3.8,<4.0)
Requires-Dist: requests (>=2.31,<3.0)
Project-URL: Bug Tracker, https://github.com/cla-bit/MonnifyEase/issues
Project-URL: Documentation, https://monnifyease.readthedocs.io/en/latest/
Project-URL: Homepage, https://github.com/cla-bit/MonnifyEase
Project-URL: Source Code, https://github.com/cla-bit/MonnifyEase
